autobox/__init__.py
autobox/constant.py
autobox/default.py
autobox/default.pyi
autobox/enum.py
autobox/filter.py
autobox/filter.pyi
autobox/parameter.py
autobox/parameter.pyi
autobox/script.py
autobox/toolbox.py
autobox/toolset.py
autobox/type.py
autobox/util.py
autobox-0.4.0.dist-info/licenses/LICENSE
autobox-0.4.0.dist-info/METADATA
autobox-0.4.0.dist-info/WHEEL
autobox-0.4.0.dist-info/top_level.txt
autobox-0.4.0.dist-info/RECORD
