Metadata-Version: 2.4
Name: autobox
Version: 0.4.0
Summary: Automation for ArcGIS Pro toolboxes, script tools, and documentation from Python objects.
Author-email: "Integrated Informatics (USA) Inc." <contact@integrated-informatics.com>
License-Expression: MIT
Project-URL: Homepage, https://github.com/realiii/autobox
Keywords: toolbox,geoprocessing,ArcGIS
Classifier: Programming Language :: Python
Classifier: Programming Language :: Python :: 3
Classifier: Programming Language :: Python :: 3.11
Classifier: Programming Language :: Python :: 3.12
Classifier: Programming Language :: Python :: 3.13
Classifier: Programming Language :: Python :: 3.14
Classifier: Operating System :: OS Independent
Requires-Python: >=3.11
License-File: LICENSE
Provides-Extra: dev
Requires-Dist: pytest; extra == "dev"
Requires-Dist: pytest-cov; extra == "dev"
Requires-Dist: coverage; extra == "dev"
Requires-Dist: twine; extra == "dev"
Requires-Dist: build; extra == "dev"
Dynamic: license-file
